superyngo_logger/__init__.py
superyngo_logger/config.py
superyngo_logger/logger_module.py
superyngo_logger-0.0.2.dist-info/METADATA
superyngo_logger-0.0.2.dist-info/WHEEL
superyngo_logger-0.0.2.dist-info/licenses/LICENSE
superyngo_logger-0.0.2.dist-info/RECORD
