Metadata-Version: 2.4
Name: superyngo-logger
Version: 0.0.2
Summary: A simple and efficient logging utility for Python applications
Project-URL: Homepage, https://github.com/superyngo/my_logger
Project-URL: Repository, https://github.com/superyngo/my_logger
Project-URL: Issues, https://github.com/superyngo/my_logger/issues
Project-URL: Changelog, https://github.com/superyngo/my_logger/blob/main/CHANGELOG.md
Author-email: Wenyang <superyngo@gmail.com>
Maintainer-email: Wenyang <superyngo@gmail.com>
License: MIT
License-File: LICENSE
Keywords: cleanup,file-rotation,logging,python,utility
Classifier: Development Status :: 4 - Beta
Classifier: Intended Audience :: Developers
Classifier: License :: OSI Approved :: MIT License
Classifier: Operating System :: OS Independent
Classifier: Programming Language :: Python :: 3
Classifier: Programming Language :: Python :: 3.8
Classifier: Programming Language :: Python :: 3.9
Classifier: Programming Language :: Python :: 3.10
Classifier: Programming Language :: Python :: 3.11
Classifier: Programming Language :: Python :: 3.12
Classifier: Topic :: Software Development :: Libraries :: Python Modules
Classifier: Topic :: System :: Logging
Requires-Python: >=3.8
Provides-Extra: dev
Requires-Dist: black; extra == 'dev'
Requires-Dist: build; extra == 'dev'
Requires-Dist: flake8; extra == 'dev'
Requires-Dist: isort; extra == 'dev'
Requires-Dist: mypy; extra == 'dev'
Requires-Dist: pytest-cov; extra == 'dev'
Requires-Dist: pytest>=6.0; extra == 'dev'
Requires-Dist: twine; extra == 'dev'
